foobot_async/__init__.py
tests/__init__.py
tests/test_foobot_async.py
foobot_async-0.3.2.dist-info/METADATA
foobot_async-0.3.2.dist-info/WHEEL
foobot_async-0.3.2.dist-info/top_level.txt
foobot_async-0.3.2.dist-info/zip-safe
foobot_async-0.3.2.dist-info/RECORD
