Metadata-Version: 2.1
Name: foobot-async
Version: 0.3.2
Summary: UNKNOWN
Home-page: https://github.com/reefab/foobot_async
Author: Fabien Piuzzi
Author-email: fabien@reefab.net
License: MIT
Platform: UNKNOWN
Classifier: Development Status :: 4 - Beta
Classifier: License :: OSI Approved :: MIT License
Classifier: Programming Language :: Python
Classifier: Programming Language :: Python :: 3.5
Classifier: Programming Language :: Python :: 3.6
Classifier: Programming Language :: Python :: 3.7
Classifier: Programming Language :: Python :: 3.8
Requires-Dist: aiohttp (>=3.6.2)
Requires-Dist: async-timeout
